geocurrency/__init__.py
geocurrency/settings.example.py
geocurrency/urls.example.py
geocurrency/urls.py
geocurrency/calculations/__init__.py
geocurrency/calculations/apps.py
geocurrency/calculations/exceptions.py
geocurrency/calculations/models.py
geocurrency/calculations/renderers.py
geocurrency/calculations/serializers.py
geocurrency/calculations/tests.py
geocurrency/calculations/urls.py
geocurrency/calculations/viewsets.py
geocurrency/converters/__init__.py
geocurrency/converters/apps.py
geocurrency/converters/models.py
geocurrency/converters/serializers.py
geocurrency/converters/views.py
geocurrency/core/__init__.py
geocurrency/core/apps.py
geocurrency/core/helpers.py
geocurrency/core/pagination.py
geocurrency/core/serializers.py
geocurrency/core/settings.py
geocurrency/core/fixtures/base_user.json
geocurrency/countries/__init__.py
geocurrency/countries/apps.py
geocurrency/countries/helpers.py
geocurrency/countries/models.py
geocurrency/countries/permissions.py
geocurrency/countries/serializers.py
geocurrency/countries/settings.py
geocurrency/countries/tests.py
geocurrency/countries/urls.py
geocurrency/countries/views.py
geocurrency/countries/viewsets.py
geocurrency/countries/services/__init__.py
geocurrency/countries/services/google.py
geocurrency/countries/services/pelias.py
geocurrency/countries/tmp/__init__.py
geocurrency/currencies/__init__.py
geocurrency/currencies/apps.py
geocurrency/currencies/filters.py
geocurrency/currencies/models.py
geocurrency/currencies/permissions.py
geocurrency/currencies/serializers.py
geocurrency/currencies/settings.py
geocurrency/currencies/tests.py
geocurrency/currencies/urls.py
geocurrency/currencies/viewsets.py
geocurrency/locale/af/LC_MESSAGES/django.mo
geocurrency/locale/ar/LC_MESSAGES/django.mo
geocurrency/locale/ar-dz/LC_MESSAGES/django.mo
geocurrency/locale/ast/LC_MESSAGES/django.mo
geocurrency/locale/az/LC_MESSAGES/django.mo
geocurrency/locale/be/LC_MESSAGES/django.mo
geocurrency/locale/bg/LC_MESSAGES/django.mo
geocurrency-0.20.0.dist-info/LICENSE
geocurrency-0.20.0.dist-info/METADATA
geocurrency-0.20.0.dist-info/WHEEL
geocurrency-0.20.0.dist-info/top_level.txt
geocurrency-0.20.0.dist-info/RECORD
