Metadata-Version: 2.1
Name: geocurrency
Version: 0.20.0
Summary: Web based services to convert units and currencies.
Home-page: https://api.geocurrency.me/swagger/
Author: Frédéric MEUROU
Author-email: fm@peabytes.me
License: UNKNOWN
Platform: UNKNOWN
Classifier: Intended Audience :: Information Technology
Classifier: Intended Audience :: Science/Research
Classifier: Environment :: Web Environment
Classifier: Development Status :: 4 - Beta
Classifier: Framework :: Django
Classifier: Framework :: Django :: 3.1
Classifier: Framework :: Django :: 3.2
Classifier: Operating System :: OS Independent
Classifier: Programming Language :: Python
Classifier: Programming Language :: Python :: 3
Classifier: Programming Language :: Python :: 3 :: Only
Classifier: Programming Language :: Python :: 3.7
Classifier: Programming Language :: Python :: 3.8
Classifier: Programming Language :: Python :: 3.9
Classifier: Programming Language :: Python :: Implementation :: CPython
Classifier: Programming Language :: Python :: Implementation :: PyPy
Classifier: Topic :: Internet :: WWW/HTTP
Classifier: Topic :: Scientific/Engineering :: Mathematics
Classifier: Topic :: Scientific/Engineering :: Physics
Classifier: Topic :: Office/Business
Classifier: License :: OSI Approved :: MIT License
Requires-Python: >3.7.0
Requires-Dist: Django (~=3.0)
Requires-Dist: django-cors-headers (~=3.2)
Requires-Dist: django-cors-middleware (~=1.5)
Requires-Dist: django-createsuperuser
Requires-Dist: django-extensions (~=3.0)
Requires-Dist: django-filter (~=2.3)
Requires-Dist: django-redis (~=4.12)
Requires-Dist: django-sendfile (~=0.3)
Requires-Dist: djangorestframework (~=3.11)
Requires-Dist: drf-yasg (~=1.17)
Requires-Dist: markdown (~=3.0)
Requires-Dist: lxml (~=4.0)
Requires-Dist: django-redis (~=4.0)
Requires-Dist: pysendfile (~=2.0)
Requires-Dist: gunicorn
Requires-Dist: requests
Requires-Dist: pytz
Requires-Dist: pycountry
Requires-Dist: countryinfo (~=0.1)
Requires-Dist: timezonefinder (~=4.4)
Requires-Dist: iso4217
Requires-Dist: forex-python (~=1.0)
Requires-Dist: Babel (~=2.8)
Requires-Dist: Pint (~=0.17)
Requires-Dist: networkx (~=2.5)
Requires-Dist: sympy (~=1.7)
Requires-Dist: channels (~=3.0)
Requires-Dist: uncertainties (~=3.1)
